odoo/addons/shopinvader_product_attribute_set/README.rst
odoo/addons/shopinvader_product_attribute_set/__init__.py
odoo/addons/shopinvader_product_attribute_set/__manifest__.py
odoo/addons/shopinvader_product_attribute_set/data/ir_export_product.xml
odoo/addons/shopinvader_product_attribute_set/demo/product_filter.xml
odoo/addons/shopinvader_product_attribute_set/i18n/shopinvader_product_attribute_set.pot
odoo/addons/shopinvader_product_attribute_set/models/__init__.py
odoo/addons/shopinvader_product_attribute_set/models/attribute_attribute.py
odoo/addons/shopinvader_product_attribute_set/models/product_filter.py
odoo/addons/shopinvader_product_attribute_set/models/shopinvader_variant.py
odoo/addons/shopinvader_product_attribute_set/readme/CONTRIBUTORS.rst
odoo/addons/shopinvader_product_attribute_set/readme/DESCRIPTION.rst
odoo/addons/shopinvader_product_attribute_set/static/description/index.html
odoo/addons/shopinvader_product_attribute_set/tests/__init__.py
odoo/addons/shopinvader_product_attribute_set/tests/test_product.py
odoo/addons/shopinvader_product_attribute_set/views/product_filter_view.xml
odoo14_addon_shopinvader_product_attribute_set-14.0.1.0.1.dev5.dist-info/METADATA
odoo14_addon_shopinvader_product_attribute_set-14.0.1.0.1.dev5.dist-info/WHEEL
odoo14_addon_shopinvader_product_attribute_set-14.0.1.0.1.dev5.dist-info/top_level.txt
odoo14_addon_shopinvader_product_attribute_set-14.0.1.0.1.dev5.dist-info/RECORD
